datacrawl/__init__.py
datacrawl/core/__init__.py
datacrawl/core/crawl_settings.py
datacrawl/core/crawler.py
datacrawl/core/datacrawl.py
datacrawl/core/spider.py
datacrawl/logger.py
datacrawl/middlewares/__init__.py
datacrawl/networking/__init__.py
datacrawl/networking/fetcher.py
datacrawl/networking/formatter.py
datacrawl/networking/robots_txt.py
datacrawl/networking/validator.py
datacrawl/webdrivers/__init__.py
datacrawl-0.6.1.dist-info/LICENSE
datacrawl-0.6.1.dist-info/METADATA
datacrawl-0.6.1.dist-info/WHEEL
datacrawl-0.6.1.dist-info/entry_points.txt
datacrawl-0.6.1.dist-info/RECORD
