Metadata-Version: 2.1
Name: datacrawl
Version: 0.6.1
Summary: A simple and efficient web crawler in Python.
Home-page: http://github.com/DataCrawl-AI/datacrawl
License: GPL-3.0-or-later
Author: Indrajith Indraprastham
Author-email: indr4jith@gmail.com
Requires-Python: >=3.8,<4.0
Classifier: License :: OSI Approved :: GNU General Public License v3 or later (GPLv3+)
Classifier: Programming Language :: Python :: 3
Classifier: Programming Language :: Python :: 3.8
Classifier: Programming Language :: Python :: 3.9
Classifier: Programming Language :: Python :: 3.10
Classifier: Programming Language :: Python :: 3.11
Classifier: Programming Language :: Python :: 3.12
Requires-Dist: aiohttp (>=3.10.0,<4.0.0)
Requires-Dist: aioresponses (>=0.7.6,<0.8.0)
Requires-Dist: beautifulsoup4 (>=4.12.3,<5.0.0)
Requires-Dist: colorama (>=0.4.6,<0.5.0)
Requires-Dist: lxml (>=5.2.2,<6.0.0)
Requires-Dist: pytest-asyncio (>=0.23.8,<0.24.0)
Requires-Dist: requests (>=2.32.3,<3.0.0)
Requires-Dist: types-requests (>=2.32.0.20240712,<3.0.0.0)
Requires-Dist: types-setuptools (>=71.1.0.20240726,<72.0.0.0)
Requires-Dist: validators (>=0.28.3,<0.29.0)
Project-URL: Documentation, http://github.com/DataCrawl-AI/datacrawl
Project-URL: Repository, http://github.com/DataCrawl-AI/datacrawl
